lsgpu/__about__.py
lsgpu/__init__.py
lsgpu-0.0.1.dist-info/METADATA
lsgpu-0.0.1.dist-info/WHEEL
lsgpu-0.0.1.dist-info/licenses/LICENSE.txt
lsgpu-0.0.1.dist-info/RECORD
